LICENSE
MANIFEST.in
README.rst
pavement.py
requirements-dev.txt
requirements.txt
setup.py
tox.ini
docs/Makefile
docs/make.bat
docs/source/README
docs/source/conf.py
docs/source/index.rst
docs/source/_static/.gitkeep
sdataflow/__init__.py
sdataflow/main.py
sdataflow/metadata.py
sdataflow/shared.py
sdataflow/synopsis.py
sdataflow.egg-info/PKG-INFO
sdataflow.egg-info/SOURCES.txt
sdataflow.egg-info/dependency_links.txt
sdataflow.egg-info/entry_points.txt
sdataflow.egg-info/not-zip-safe
sdataflow.egg-info/top_level.txt
sdataflow/callback/__init__.py
sdataflow/callback/helper.py
sdataflow/callback/register.py
sdataflow/callback/scheduler.py
sdataflow/debug/__init__.py
sdataflow/debug/mermaid.full.js
sdataflow/debug/mermaid_page.py
sdataflow/lang/__init__.py
sdataflow/lang/analysis.py
sdataflow/lang/generated_lextab.py
sdataflow/lang/generated_parsetab.py
sdataflow/lang/lexer.py
sdataflow/lang/parser.py
tests/README.md
tests/callback/test_register.py
tests/callback/test_scheduler.py
tests/debug/test_mermaid_page.py
tests/lang/test_analysis.py
tests/lang/test_init.py
tests/lang/test_lexer.py
tests/lang/test_parser.py