Metadata-Version: 1.1
Name: sdataflow
Version: 0.3.2-rc-1
Summary: A simple language to describe dataflow between entries, implemented in Python.
Home-page: https://github.com/haoxun/sdataflow
Author: Zhan Haoxun
Author-email: programmer.zhx@gmail.com
License: UNKNOWN
Platform: UNKNOWN
Classifier: Development Status :: 1 - Planning
Classifier: Environment :: Console
Classifier: Intended Audience :: Developers
Classifier: License :: OSI Approved :: MIT License
Classifier: Natural Language :: English
Classifier: Operating System :: OS Independent
Classifier: Programming Language :: Python :: 2.7
Classifier: Programming Language :: Python :: 3.4
Classifier: Topic :: Documentation
Classifier: Topic :: Software Development :: Libraries :: Python Modules
Classifier: Topic :: System :: Installation/Setup
Classifier: Topic :: System :: Software Distribution
